macholibre/__init__.py
macholibre/dictionary.py
macholibre/parser.py
ak_macholibre-1.1.0.post3.dist-info/LICENSE
ak_macholibre-1.1.0.post3.dist-info/METADATA
ak_macholibre-1.1.0.post3.dist-info/WHEEL
ak_macholibre-1.1.0.post3.dist-info/entry_points.txt
ak_macholibre-1.1.0.post3.dist-info/top_level.txt
ak_macholibre-1.1.0.post3.dist-info/RECORD
