Metadata-Version: 2.1
Name: ak-macholibre
Version: 1.1.0.post3
Summary: Mach-O & Universal Binary Parser
Home-page: UNKNOWN
Author: Aaron Stephens
Author-email: aaronjst93@gmail.com
License: Apache License 2.0
Keywords: mach-o universal binary parser mac apple json
Platform: UNKNOWN
Requires-Dist: asn1crypto
